addIt/hexdisplay.vhd
library IEEE;
use IEEE.STD_LOGIC_1164.ALL;
use IEEE.NUMERIC_STD.ALL;

entity hexdisplay is
    Port ( 
			in_port : IN UNSIGNED(3 downto 0);
			out_port: OUT UNSIGNED(6 downto 0)
		);
end hexdisplay;

architecture Behavioral of hexdisplay is
begin
process(in_port)
    variable temp : UNSIGNED(6 downto 0);
begin
    case to_integer(in_port) is
         when 0 => temp := "0111111"; -- 0
			when 1 => temp := "0000110"; -- 1
			when 2 => temp := "1011011"; -- 2
			when 3 => temp := "1001111"; -- 3
			when 4 => temp := "1100110"; -- 4
			when 5 => temp := "1101101"; -- 5
			when 6 => temp := "1111101"; -- 6
			when 7 => temp := "0000111"; -- 7
			when 8 => temp := "1111111"; -- 8
			when 9 => temp := "1101111"; -- 9
			when 10 => temp := "1110111"; -- A
			when 11 => temp := "1111100"; -- B
			when 12 => temp := "0111001"; -- C
			when 13 => temp := "1011110"; -- D
			when 14 => temp := "1111001"; -- E
			when 15 => temp := "1110001"; -- F
			when others => temp := "0000000"; -- Default to off
    end case;
    out_port <= temp;
end process;
end Behavioral;

addIt/addIt.vhd
library IEEE;
use IEEE.STD_LOGIC_1164.ALL;
use IEEE.numeric_std.ALL;

entity addIt is
    Port ( A : in  UNSIGNED (3 downto 0);
           B : in  UNSIGNED (3 downto 0);
           C : out UNSIGNED (4 downto 0));
end addIt;

architecture Behavioral of addIt is
begin
    process(A, B)
    begin
        C <= ('0' & A) + ('0' & B);
    end process;
end Behavioral;

addIt/addItbench.vhd
library IEEE;
use IEEE.STD_LOGIC_1164.ALL;
use IEEE.numeric_std.ALL;

entity addItbench is
end addItbench;

architecture sim of addItbench is
    signal A, B: UNSIGNED(3 downto 0);
    signal C: UNSIGNED(4 downto 0);
    signal hexDisplay1, hexDisplay2: UNSIGNED(3 downto 0);

    -- Instantiate the addIt
    component addIt
        Port ( A : in  UNSIGNED (3 downto 0);
               B : in  UNSIGNED (3 downto 0);
               C : out UNSIGNED (4 downto 0));
    end component;

    -- Assuming a hexdisplay component with the following interface
    component hexdisplay
        Port ( 
               in_port : in UNSIGNED(3 downto 0);
               out_port: out UNSIGNED(6 downto 0)
             );
    end component;

begin
    -- Connect the addIt
    UUT: addIt port map (
        A => A,
        B => B,
        C => C
    );

    -- Connect the hex displays
    hexDisplay1 <= C(3 downto 0);
    hexDisplay2 <= "000" & C(4);

    hex1: hexdisplay port map (hexDisplay1);
    hex2: hexdisplay port map (hexDisplay2);

    -- Testbench stimulus process
    process
    begin
        for i in 0 to 15 loop
            for j in 0 to 15 loop
                A <= to_unsigned(i, 4);
                B <= to_unsigned(j, 4);
                wait for 10 ns;  -- Adjust the delay as needed
            end loop;
        end loop;
        wait;
    end process;

end sim;

addIt/addItbench.vcd
$date
  Wed Oct 11 00:09:52 2023
$end
$version
  GHDL v0
$end
$timescale
  1 fs
$end
$scope module standard $end
$upscope $end
$scope module std_logic_1164 $end
$upscope $end
$scope module numeric_std $end
$upscope $end
$scope module additbench $end
$var reg 4 ! a[3:0] $end
$var reg 4 " b[3:0] $end
$var reg 5 # c[4:0] $end
$var reg 4 $ hexdisplay1[3:0] $end
$var reg 4 % hexdisplay2[3:0] $end
$scope module uut $end
$var reg 4 & a[3:0] $end
$var reg 4 ' b[3:0] $end
$var reg 5 ( c[4:0] $end
$upscope $end
$scope module hex1 $end
$var reg 4 ) in_port[3:0] $end
$var reg 7 * out_port[6:0] $end
$upscope $end
$scope module hex2 $end
$var reg 4 + in_port[3:0] $end
$var reg 7 , out_port[6:0] $end
$upscope $end
$upscope $end
$enddefinitions $end
#0
b0000 !
b0000 "
b00000 #
b0000 $
b0000 %
b0000 &
b0000 '
b00000 (
b0000 )
b0111111 *
b0000 +
b0111111 ,
#10000000
b0001 "
b00001 #
b0001 $
b0001 '
b00001 (
b0001 )
b0000110 *
#20000000
b0010 "
b00010 #
b0010 $
b0010 '
b00010 (
b0010 )
b1011011 *
#30000000
b0011 "
b00011 #
b0011 $
b0011 '
b00011 (
b0011 )
b1001111 *
#40000000
b0100 "
b00100 #
b0100 $
b0100 '
b00100 (
b0100 )
b1100110 *
#50000000
b0101 "
b00101 #
b0101 $
b0101 '
b00101 (
b0101 )
b1101101 *
#60000000
b0110 "
b00110 #
b0110 $
b0110 '
b00110 (
b0110 )
b1111101 *
#70000000
b0111 "
b00111 #
b0111 $
b0111 '
b00111 (
b0111 )
b0000111 *
#80000000
b1000 "
b01000 #
b1000 $
b1000 '
b01000 (
b1000 )
b1111111 *
#90000000
b1001 "
b01001 #
b1001 $
b1001 '
b01001 (
b1001 )
b1101111 *
#100000000
b1010 "
b01010 #
b1010 $
b1010 '
b01010 (
b1010 )
b1110111 *
#110000000
b1011 "
b01011 #
b1011 $
b1011 '
b01011 (
b1011 )
b1111100 *
#120000000
b1100 "
b01100 #
b1100 $
b1100 '
b01100 (
b1100 )
b0111001 *
#130000000
b1101 "
b01101 #
b1101 $
b1101 '
b01101 (
b1101 )
b1011110 *
#140000000
b1110 "
b01110 #
b1110 $
b1110 '
b01110 (
b1110 )
b1111001 *
#150000000
b1111 "
b01111 #
b1111 $
b1111 '
b01111 (
b1111 )
b1110001 *
#160000000
b0001 !
b0000 "
b00001 #
b0001 $
b0001 &
b0000 '
b00001 (
b0001 )
b0000110 *
#170000000
b0001 "
b00010 #
b0010 $
b0001 '
b00010 (
b0010 )
b1011011 *
#180000000
b0010 "
b00011 #
b0011 $
b0010 '
b00011 (
b0011 )
b1001111 *
#190000000
b0011 "
b00100 #
b0100 $
b0011 '
b00100 (
b0100 )
b1100110 *
#200000000
b0100 "
b00101 #
b0101 $
b0100 '
b00101 (
b0101 )
b1101101 *
#210000000
b0101 "
b00110 #
b0110 $
b0101 '
b00110 (
b0110 )
b1111101 *
#220000000
b0110 "
b00111 #
b0111 $
b0110 '
b00111 (
b0111 )
b0000111 *
#230000000
b0111 "
b01000 #
b1000 $
b0111 '
b01000 (
b1000 )
b1111111 *
#240000000
b1000 "
b01001 #
b1001 $
b1000 '
b01001 (
b1001 )
b1101111 *
#250000000
b1001 "
b01010 #
b1010 $
b1001 '
b01010 (
b1010 )
b1110111 *
#260000000
b1010 "
b01011 #
b1011 $
b1010 '
b01011 (
b1011 )
b1111100 *
#270000000
b1011 "
b01100 #
b1100 $
b1011 '
b01100 (
b1100 )
b0111001 *
#280000000
b1100 "
b01101 #
b1101 $
b1100 '
b01101 (
b1101 )
b1011110 *
#290000000
b1101 "
b01110 #
b1110 $
b1101 '
b01110 (
b1110 )
b1111001 *
#300000000
b1110 "
b01111 #
b1111 $
b1110 '
b01111 (
b1111 )
b1110001 *
#310000000
b1111 "
b10000 #
b0000 $
b0001 %
b1111 '
b10000 (
b0000 )
b0111111 *
b0001 +
b0000110 ,
#320000000
b0010 !
b0000 "
b00010 #
b0010 $
b0000 %
b0010 &
b0000 '
b00010 (
b0010 )
b1011011 *
b0000 +
b0111111 ,
#330000000
b0001 "
b00011 #
b0011 $
b0001 '
b00011 (
b0011 )
b1001111 *
#340000000
b0010 "
b00100 #
b0100 $
b0010 '
b00100 (
b0100 )
b1100110 *
#350000000
b0011 "
b00101 #
b0101 $
b0011 '
b00101 (
b0101 )
b1101101 *
#360000000
b0100 "
b00110 #
b0110 $
b0100 '
b00110 (
b0110 )
b1111101 *
#370000000
b0101 "
b00111 #
b0111 $
b0101 '
b00111 (
b0111 )
b0000111 *
#380000000
b0110 "
b01000 #
b1000 $
b0110 '
b01000 (
b1000 )
b1111111 *
#390000000
b0111 "
b01001 #
b1001 $
b0111 '
b01001 (
b1001 )
b1101111 *
#400000000
b1000 "
b01010 #
b1010 $
b1000 '
b01010 (
b1010 )
b1110111 *
#410000000
b1001 "
b01011 #
b1011 $
b1001 '
b01011 (
b1011 )
b1111100 *
#420000000
b1010 "
b01100 #
b1100 $
b1010 '
b01100 (
b1100 )
b0111001 *
#430000000
b1011 "
b01101 #
b1101 $
b1011 '
b01101 (
b1101 )
b1011110 *
#440000000
b1100 "
b01110 #
b1110 $
b1100 '
b01110 (
b1110 )
b1111001 *
#450000000
b1101 "
b01111 #
b1111 $
b1101 '
b01111 (
b1111 )
b1110001 *
#460000000
b1110 "
b10000 #
b0000 $
b0001 %
b1110 '
b10000 (
b0000 )
b0111111 *
b0001 +
b0000110 ,
#470000000
b1111 "
b10001 #
b0001 $
b1111 '
b10001 (
b0001 )
b0000110 *
#480000000
b0011 !
b0000 "
b00011 #
b0011 $
b0000 %
b0011 &
b0000 '
b00011 (
b0011 )
b1001111 *
b0000 +
b0111111 ,
#490000000
b0001 "
b00100 #
b0100 $
b0001 '
b00100 (
b0100 )
b1100110 *
#500000000
b0010 "
b00101 #
b0101 $
b0010 '
b00101 (
b0101 )
b1101101 *
#510000000
b0011 "
b00110 #
b0110 $
b0011 '
b00110 (
b0110 )
b1111101 *
#520000000
b0100 "
b00111 #
b0111 $
b0100 '
b00111 (
b0111 )
b0000111 *
#530000000
b0101 "
b01000 #
b1000 $
b0101 '
b01000 (
b1000 )
b1111111 *
#540000000
b0110 "
b01001 #
b1001 $
b0110 '
b01001 (
b1001 )
b1101111 *
#550000000
b0111 "
b01010 #
b1010 $
b0111 '
b01010 (
b1010 )
b1110111 *
#560000000
b1000 "
b01011 #
b1011 $
b1000 '
b01011 (
b1011 )
b1111100 *
#570000000
b1001 "
b01100 #
b1100 $
b1001 '
b01100 (
b1100 )
b0111001 *
#580000000
b1010 "
b01101 #
b1101 $
b1010 '
b01101 (
b1101 )
b1011110 *
#590000000
b1011 "
b01110 #
b1110 $
b1011 '
b01110 (
b1110 )
b1111001 *
#600000000
b1100 "
b01111 #
b1111 $
b1100 '
b01111 (
b1111 )
b1110001 *
#610000000
b1101 "
b10000 #
b0000 $
b0001 %
b1101 '
b10000 (
b0000 )
b0111111 *
b0001 +
b0000110 ,
#620000000
b1110 "
b10001 #
b0001 $
b1110 '
b10001 (
b0001 )
b0000110 *
#630000000
b1111 "
b10010 #
b0010 $
b1111 '
b10010 (
b0010 )
b1011011 *
#640000000
b0100 !
b0000 "
b00100 #
b0100 $
b0000 %
b0100 &
b0000 '
b00100 (
b0100 )
b1100110 *
b0000 +
b0111111 ,
#650000000
b0001 "
b00101 #
b0101 $
b0001 '
b00101 (
b0101 )
b1101101 *
#660000000
b0010 "
b00110 #
b0110 $
b0010 '
b00110 (
b0110 )
b1111101 *
#670000000
b0011 "
b00111 #
b0111 $
b0011 '
b00111 (
b0111 )
b0000111 *
#680000000
b0100 "
b01000 #
b1000 $
b0100 '
b01000 (
b1000 )
b1111111 *
#690000000
b0101 "
b01001 #
b1001 $
b0101 '
b01001 (
b1001 )
b1101111 *
#700000000
b0110 "
b01010 #
b1010 $
b0110 '
b01010 (
b1010 )
b1110111 *
#710000000
b0111 "
b01011 #
b1011 $
b0111 '
b01011 (
b1011 )
b1111100 *
#720000000
b1000 "
b01100 #
b1100 $
b1000 '
b01100 (
b1100 )
b0111001 *
#730000000
b1001 "
b01101 #
b1101 $
b1001 '
b01101 (
b1101 )
b1011110 *
#740000000
b1010 "
b01110 #
b1110 $
b1010 '
b01110 (
b1110 )
b1111001 *
#750000000
b1011 "
b01111 #
b1111 $
b1011 '
b01111 (
b1111 )
b1110001 *
#760000000
b1100 "
b10000 #
b0000 $
b0001 %
b1100 '
b10000 (
b0000 )
b0111111 *
b0001 +
b0000110 ,
#770000000
b1101 "
b10001 #
b0001 $
b1101 '
b10001 (
b0001 )
b0000110 *
#780000000
b1110 "
b10010 #
b0010 $
b1110 '
b10010 (
b0010 )
b1011011 *
#790000000
b1111 "
b10011 #
b0011 $
b1111 '
b10011 (
b0011 )
b1001111 *
#800000000
b0101 !
b0000 "
b00101 #
b0101 $
b0000 %
b0101 &
b0000 '
b00101 (
b0101 )
b1101101 *
b0000 +
b0111111 ,
#810000000
b0001 "
b00110 #
b0110 $
b0001 '
b00110 (
b0110 )
b1111101 *
#820000000
b0010 "
b00111 #
b0111 $
b0010 '
b00111 (
b0111 )
b0000111 *
#830000000
b0011 "
b01000 #
b1000 $
b0011 '
b01000 (
b1000 )
b1111111 *
#840000000
b0100 "
b01001 #
b1001 $
b0100 '
b01001 (
b1001 )
b1101111 *
#850000000
b0101 "
b01010 #
b1010 $
b0101 '
b01010 (
b1010 )
b1110111 *
#860000000
b0110 "
b01011 #
b1011 $
b0110 '
b01011 (
b1011 )
b1111100 *
#870000000
b0111 "
b01100 #
b1100 $
b0111 '
b01100 (
b1100 )
b0111001 *
#880000000
b1000 "
b01101 #
b1101 $
b1000 '
b01101 (
b1101 )
b1011110 *
#890000000
b1001 "
b01110 #
b1110 $
b1001 '
b01110 (
b1110 )
b1111001 *
#900000000
b1010 "
b01111 #
b1111 $
b1010 '
b01111 (
b1111 )
b1110001 *
#910000000
b1011 "
b10000 #
b0000 $
b0001 %
b1011 '
b10000 (
b0000 )
b0111111 *
b0001 +
b0000110 ,
#920000000
b1100 "
b10001 #
b0001 $
b1100 '
b10001 (
b0001 )
b0000110 *
#930000000
b1101 "
b10010 #
b0010 $
b1101 '
b10010 (
b0010 )
b1011011 *
#940000000
b1110 "
b10011 #
b0011 $
b1110 '
b10011 (
b0011 )
b1001111 *
#950000000
b1111 "
b10100 #
b0100 $
b1111 '
b10100 (
b0100 )
b1100110 *
#960000000
b0110 !
b0000 "
b00110 #
b0110 $
b0000 %
b0110 &
b0000 '
b00110 (
b0110 )
b1111101 *
b0000 +
b0111111 ,
#970000000
b0001 "
b00111 #
b0111 $
b0001 '
b00111 (
b0111 )
b0000111 *
#980000000
b0010 "
b01000 #
b1000 $
b0010 '
b01000 (
b1000 )
b1111111 *
#990000000
b0011 "
b01001 #
b1001 $
b0011 '
b01001 (
b1001 )
b1101111 *
#1000000000
b0100 "
b01010 #
b1010 $
b0100 '
b01010 (
b1010 )
b1110111 *
#1010000000
b0101 "
b01011 #
b1011 $
b0101 '
b01011 (
b1011 )
b1111100 *
#1020000000
b0110 "
b01100 #
b1100 $
b0110 '
b01100 (
b1100 )
b0111001 *
#1030000000
b0111 "
b01101 #
b1101 $
b0111 '
b01101 (
b1101 )
b1011110 *
#1040000000
b1000 "
b01110 #
b1110 $
b1000 '
b01110 (
b1110 )
b1111001 *
#1050000000
b1001 "
b01111 #
b1111 $
b1001 '
b01111 (
b1111 )
b1110001 *
#1060000000
b1010 "
b10000 #
b0000 $
b0001 %
b1010 '
b10000 (
b0000 )
b0111111 *
b0001 +
b0000110 ,
#1070000000
b1011 "
b10001 #
b0001 $
b1011 '
b10001 (
b0001 )
b0000110 *
#1080000000
b1100 "
b10010 #
b0010 $
b1100 '
b10010 (
b0010 )
b1011011 *
#1090000000
b1101 "
b10011 #
b0011 $
b1101 '
b10011 (
b0011 )
b1001111 *
#1100000000
b1110 "
b10100 #
b0100 $
b1110 '
b10100 (
b0100 )
b1100110 *
#1110000000
b1111 "
b10101 #
b0101 $
b1111 '
b10101 (
b0101 )
b1101101 *
#1120000000
b0111 !
b0000 "
b00111 #
b0111 $
b0000 %
b0111 &
b0000 '
b00111 (
b0111 )
b0000111 *
b0000 +
b0111111 ,
#1130000000
b0001 "
b01000 #
b1000 $
b0001 '
b01000 (
b1000 )
b1111111 *
#1140000000
b0010 "
b01001 #
b1001 $
b0010 '
b01001 (
b1001 )
b1101111 *
#1150000000
b0011 "
b01010 #
b1010 $
b0011 '
b01010 (
b1010 )
b1110111 *
#1160000000
b0100 "
b01011 #
b1011 $
b0100 '
b01011 (
b1011 )
b1111100 *
#1170000000
b0101 "
b01100 #
b1100 $
b0101 '
b01100 (
b1100 )
b0111001 *
#1180000000
b0110 "
b01101 #
b1101 $
b0110 '
b01101 (
b1101 )
b1011110 *
#1190000000
b0111 "
b01110 #
b1110 $
b0111 '
b01110 (
b1110 )
b1111001 *
#1200000000
b1000 "
b01111 #
b1111 $
b1000 '
b01111 (
b1111 )
b1110001 *
#1210000000
b1001 "
b10000 #
b0000 $
b0001 %
b1001 '
b10000 (
b0000 )
b0111111 *
b0001 +
b0000110 ,
#1220000000
b1010 "
b10001 #
b0001 $
b1010 '
b10001 (
b0001 )
b0000110 *
#1230000000
b1011 "
b10010 #
b0010 $
b1011 '
b10010 (
b0010 )
b1011011 *
#1240000000
b1100 "
b10011 #
b0011 $
b1100 '
b10011 (
b0011 )
b1001111 *
#1250000000
b1101 "
b10100 #
b0100 $
b1101 '
b10100 (
b0100 )
b1100110 *
#1260000000
b1110 "
b10101 #
b0101 $
b1110 '
b10101 (
b0101 )
b1101101 *
#1270000000
b1111 "
b10110 #
b0110 $
b1111 '
b10110 (
b0110 )
b1111101 *
#1280000000
b1000 !
b0000 "
b01000 #
b1000 $
b0000 %
b1000 &
b0000 '
b01000 (
b1000 )
b1111111 *
b0000 +
b0111111 ,
#1290000000
b0001 "
b01001 #
b1001 $
b0001 '
b01001 (
b1001 )
b1101111 *
#1300000000
b0010 "
b01010 #
b1010 $
b0010 '
b01010 (
b1010 )
b1110111 *
#1310000000
b0011 "
b01011 #
b1011 $
b0011 '
b01011 (
b1011 )
b1111100 *
#1320000000
b0100 "
b01100 #
b1100 $
b0100 '
b01100 (
b1100 )
b0111001 *
#1330000000
b0101 "
b01101 #
b1101 $
b0101 '
b01101 (
b1101 )
b1011110 *
#1340000000
b0110 "
b01110 #
b1110 $
b0110 '
b01110 (
b1110 )
b1111001 *
#1350000000
b0111 "
b01111 #
b1111 $
b0111 '
b01111 (
b1111 )
b1110001 *
#1360000000
b1000 "
b10000 #
b0000 $
b0001 %
b1000 '
b10000 (
b0000 )
b0111111 *
b0001 +
b0000110 ,
#1370000000
b1001 "
b10001 #
b0001 $
b1001 '
b10001 (
b0001 )
b0000110 *
#1380000000
b1010 "
b10010 #
b0010 $
b1010 '
b10010 (
b0010 )
b1011011 *
#1390000000
b1011 "
b10011 #
b0011 $
b1011 '
b10011 (
b0011 )
b1001111 *
#1400000000
b1100 "
b10100 #
b0100 $
b1100 '
b10100 (
b0100 )
b1100110 *
#1410000000
b1101 "
b10101 #
b0101 $
b1101 '
b10101 (
b0101 )
b1101101 *
#1420000000
b1110 "
b10110 #
b0110 $
b1110 '
b10110 (
b0110 )
b1111101 *
#1430000000
b1111 "
b10111 #
b0111 $
b1111 '
b10111 (
b0111 )
b0000111 *
#1440000000
b1001 !
b0000 "
b01001 #
b1001 $
b0000 %
b1001 &
b0000 '
b01001 (
b1001 )
b1101111 *
b0000 +
b0111111 ,
#1450000000
b0001 "
b01010 #
b1010 $
b0001 '
b01010 (
b1010 )
b1110111 *
#1460000000
b0010 "
b01011 #
b1011 $
b0010 '
b01011 (
b1011 )
b1111100 *
#1470000000
b0011 "
b01100 #
b1100 $
b0011 '
b01100 (
b1100 )
b0111001 *
#1480000000
b0100 "
b01101 #
b1101 $
b0100 '
b01101 (
b1101 )
b1011110 *
#1490000000
b0101 "
b01110 #
b1110 $
b0101 '
b01110 (
b1110 )
b1111001 *
#1500000000
b0110 "
b01111 #
b1111 $
b0110 '
b01111 (
b1111 )
b1110001 *
#1510000000
b0111 "
b10000 #
b0000 $
b0001 %
b0111 '
b10000 (
b0000 )
b0111111 *
b0001 +
b0000110 ,
#1520000000
b1000 "
b10001 #
b0001 $
b1000 '
b10001 (
b0001 )
b0000110 *
#1530000000
b1001 "
b10010 #
b0010 $
b1001 '
b10010 (
b0010 )
b1011011 *
#1540000000
b1010 "
b10011 #
b0011 $
b1010 '
b10011 (
b0011 )
b1001111 *
#1550000000
b1011 "
b10100 #
b0100 $
b1011 '
b10100 (
b0100 )
b1100110 *
#1560000000
b1100 "
b10101 #
b0101 $
b1100 '
b10101 (
b0101 )
b1101101 *
#1570000000
b1101 "
b10110 #
b0110 $
b1101 '
b10110 (
b0110 )
b1111101 *
#1580000000
b1110 "
b10111 #
b0111 $
b1110 '
b10111 (
b0111 )
b0000111 *
#1590000000
b1111 "
b11000 #
b1000 $
b1111 '
b11000 (
b1000 )
b1111111 *
#1600000000
b1010 !
b0000 "
b01010 #
b1010 $
b0000 %
b1010 &
b0000 '
b01010 (
b1010 )
b1110111 *
b0000 +
b0111111 ,
#1610000000
b0001 "
b01011 #
b1011 $
b0001 '
b01011 (
b1011 )
b1111100 *
#1620000000
b0010 "
b01100 #
b1100 $
b0010 '
b01100 (
b1100 )
b0111001 *
#1630000000
b0011 "
b01101 #
b1101 $
b0011 '
b01101 (
b1101 )
b1011110 *
#1640000000
b0100 "
b01110 #
b1110 $
b0100 '
b01110 (
b1110 )
b1111001 *
#1650000000
b0101 "
b01111 #
b1111 $
b0101 '
b01111 (
b1111 )
b1110001 *
#1660000000
b0110 "
b10000 #
b0000 $
b0001 %
b0110 '
b10000 (
b0000 )
b0111111 *
b0001 +
b0000110 ,
#1670000000
b0111 "
b10001 #
b0001 $
b0111 '
b10001 (
b0001 )
b0000110 *
#1680000000
b1000 "
b10010 #
b0010 $
b1000 '
b10010 (
b0010 )
b1011011 *
#1690000000
b1001 "
b10011 #
b0011 $
b1001 '
b10011 (
b0011 )
b1001111 *
#1700000000
b1010 "
b10100 #
b0100 $
b1010 '
b10100 (
b0100 )
b1100110 *
#1710000000
b1011 "
b10101 #
b0101 $
b1011 '
b10101 (
b0101 )
b1101101 *
#1720000000
b1100 "
b10110 #
b0110 $
b1100 '
b10110 (
b0110 )
b1111101 *
#1730000000
b1101 "
b10111 #
b0111 $
b1101 '
b10111 (
b0111 )
b0000111 *
#1740000000
b1110 "
b11000 #
b1000 $
b1110 '
b11000 (
b1000 )
b1111111 *
#1750000000
b1111 "
b11001 #
b1001 $
b1111 '
b11001 (
b1001 )
b1101111 *
#1760000000
b1011 !
b0000 "
b01011 #
b1011 $
b0000 %
b1011 &
b0000 '
b01011 (
b1011 )
b1111100 *
b0000 +
b0111111 ,
#1770000000
b0001 "
b01100 #
b1100 $
b0001 '
b01100 (
b1100 )
b0111001 *
#1780000000
b0010 "
b01101 #
b1101 $
b0010 '
b01101 (
b1101 )
b1011110 *
#1790000000
b0011 "
b01110 #
b1110 $
b0011 '
b01110 (
b1110 )
b1111001 *
#1800000000
b0100 "
b01111 #
b1111 $
b0100 '
b01111 (
b1111 )
b1110001 *
#1810000000
b0101 "
b10000 #
b0000 $
b0001 %
b0101 '
b10000 (
b0000 )
b0111111 *
b0001 +
b0000110 ,
#1820000000
b0110 "
b10001 #
b0001 $
b0110 '
b10001 (
b0001 )
b0000110 *
#1830000000
b0111 "
b10010 #
b0010 $
b0111 '
b10010 (
b0010 )
b1011011 *
#1840000000
b1000 "
b10011 #
b0011 $
b1000 '
b10011 (
b0011 )
b1001111 *
#1850000000
b1001 "
b10100 #
b0100 $
b1001 '
b10100 (
b0100 )
b1100110 *
#1860000000
b1010 "
b10101 #
b0101 $
b1010 '
b10101 (
b0101 )
b1101101 *
#1870000000
b1011 "
b10110 #
b0110 $
b1011 '
b10110 (
b0110 )
b1111101 *
#1880000000
b1100 "
b10111 #
b0111 $
b1100 '
b10111 (
b0111 )
b0000111 *
#1890000000
b1101 "
b11000 #
b1000 $
b1101 '
b11000 (
b1000 )
b1111111 *
#1900000000
b1110 "
b11001 #
b1001 $
b1110 '
b11001 (
b1001 )
b1101111 *
#1910000000
b1111 "
b11010 #
b1010 $
b1111 '
b11010 (
b1010 )
b1110111 *
#1920000000
b1100 !
b0000 "
b01100 #
b1100 $
b0000 %
b1100 &
b0000 '
b01100 (
b1100 )
b0111001 *
b0000 +
b0111111 ,
#1930000000
b0001 "
b01101 #
b1101 $
b0001 '
b01101 (
b1101 )
b1011110 *
#1940000000
b0010 "
b01110 #
b1110 $
b0010 '
b01110 (
b1110 )
b1111001 *
#1950000000
b0011 "
b01111 #
b1111 $
b0011 '
b01111 (
b1111 )
b1110001 *
#1960000000
b0100 "
b10000 #
b0000 $
b0001 %
b0100 '
b10000 (
b0000 )
b0111111 *
b0001 +
b0000110 ,
#1970000000
b0101 "
b10001 #
b0001 $
b0101 '
b10001 (
b0001 )
b0000110 *
#1980000000
b0110 "
b10010 #
b0010 $
b0110 '
b10010 (
b0010 )
b1011011 *
#1990000000
b0111 "
b10011 #
b0011 $
b0111 '
b10011 (
b0011 )
b1001111 *
#2000000000
b1000 "
b10100 #
b0100 $
b1000 '
b10100 (
b0100 )
b1100110 *
#2010000000
b1001 "
b10101 #
b0101 $
b1001 '
b10101 (
b0101 )
b1101101 *
#2020000000
b1010 "
b10110 #
b0110 $
b1010 '
b10110 (
b0110 )
b1111101 *
#2030000000
b1011 "
b10111 #
b0111 $
b1011 '
b10111 (
b0111 )
b0000111 *
#2040000000
b1100 "
b11000 #
b1000 $
b1100 '
b11000 (
b1000 )
b1111111 *
#2050000000
b1101 "
b11001 #
b1001 $
b1101 '
b11001 (
b1001 )
b1101111 *
#2060000000
b1110 "
b11010 #
b1010 $
b1110 '
b11010 (
b1010 )
b1110111 *
#2070000000
b1111 "
b11011 #
b1011 $
b1111 '
b11011 (
b1011 )
b1111100 *
#2080000000
b1101 !
b0000 "
b01101 #
b1101 $
b0000 %
b1101 &
b0000 '
b01101 (
b1101 )
b1011110 *
b0000 +
b0111111 ,
#2090000000
b0001 "
b01110 #
b1110 $
b0001 '
b01110 (
b1110 )
b1111001 *
#2100000000
b0010 "
b01111 #
b1111 $
b0010 '
b01111 (
b1111 )
b1110001 *
#2110000000
b0011 "
b10000 #
b0000 $
b0001 %
b0011 '
b10000 (
b0000 )
b0111111 *
b0001 +
b0000110 ,
#2120000000
b0100 "
b10001 #
b0001 $
b0100 '
b10001 (
b0001 )
b0000110 *
#2130000000
b0101 "
b10010 #
b0010 $
b0101 '
b10010 (
b0010 )
b1011011 *
#2140000000
b0110 "
b10011 #
b0011 $
b0110 '
b10011 (
b0011 )
b1001111 *
#2150000000
b0111 "
b10100 #
b0100 $
b0111 '
b10100 (
b0100 )
b1100110 *
#2160000000
b1000 "
b10101 #
b0101 $
b1000 '
b10101 (
b0101 )
b1101101 *
#2170000000
b1001 "
b10110 #
b0110 $
b1001 '
b10110 (
b0110 )
b1111101 *
#2180000000
b1010 "
b10111 #
b0111 $
b1010 '
b10111 (
b0111 )
b0000111 *
#2190000000
b1011 "
b11000 #
b1000 $
b1011 '
b11000 (
b1000 )
b1111111 *
#2200000000
b1100 "
b11001 #
b1001 $
b1100 '
b11001 (
b1001 )
b1101111 *
#2210000000
b1101 "
b11010 #
b1010 $
b1101 '
b11010 (
b1010 )
b1110111 *
#2220000000
b1110 "
b11011 #
b1011 $
b1110 '
b11011 (
b1011 )
b1111100 *
#2230000000
b1111 "
b11100 #
b1100 $
b1111 '
b11100 (
b1100 )
b0111001 *
#2240000000
b1110 !
b0000 "
b01110 #
b1110 $
b0000 %
b1110 &
b0000 '
b01110 (
b1110 )
b1111001 *
b0000 +
b0111111 ,
#2250000000
b0001 "
b01111 #
b1111 $
b0001 '
b01111 (
b1111 )
b1110001 *
#2260000000
b0010 "
b10000 #
b0000 $
b0001 %
b0010 '
b10000 (
b0000 )
b0111111 *
b0001 +
b0000110 ,
#2270000000
b0011 "
b10001 #
b0001 $
b0011 '
b10001 (
b0001 )
b0000110 *
#2280000000
b0100 "
b10010 #
b0010 $
b0100 '
b10010 (
b0010 )
b1011011 *
#2290000000
b0101 "
b10011 #
b0011 $
b0101 '
b10011 (
b0011 )
b1001111 *
#2300000000
b0110 "
b10100 #
b0100 $
b0110 '
b10100 (
b0100 )
b1100110 *
#2310000000
b0111 "
b10101 #
b0101 $
b0111 '
b10101 (
b0101 )
b1101101 *
#2320000000
b1000 "
b10110 #
b0110 $
b1000 '
b10110 (
b0110 )
b1111101 *
#2330000000
b1001 "
b10111 #
b0111 $
b1001 '
b10111 (
b0111 )
b0000111 *
#2340000000
b1010 "
b11000 #
b1000 $
b1010 '
b11000 (
b1000 )
b1111111 *
#2350000000
b1011 "
b11001 #
b1001 $
b1011 '
b11001 (
b1001 )
b1101111 *
#2360000000
b1100 "
b11010 #
b1010 $
b1100 '
b11010 (
b1010 )
b1110111 *
#2370000000
b1101 "
b11011 #
b1011 $
b1101 '
b11011 (
b1011 )
b1111100 *
#2380000000
b1110 "
b11100 #
b1100 $
b1110 '
b11100 (
b1100 )
b0111001 *
#2390000000
b1111 "
b11101 #
b1101 $
b1111 '
b11101 (
b1101 )
b1011110 *
#2400000000
b1111 !
b0000 "
b01111 #
b1111 $
b0000 %
b1111 &
b0000 '
b01111 (
b1111 )
b1110001 *
b0000 +
b0111111 ,
#2410000000
b0001 "
b10000 #
b0000 $
b0001 %
b0001 '
b10000 (
b0000 )
b0111111 *
b0001 +
b0000110 ,
#2420000000
b0010 "
b10001 #
b0001 $
b0010 '
b10001 (
b0001 )
b0000110 *
#2430000000
b0011 "
b10010 #
b0010 $
b0011 '
b10010 (
b0010 )
b1011011 *
#2440000000
b0100 "
b10011 #
b0011 $
b0100 '
b10011 (
b0011 )
b1001111 *
#2450000000
b0101 "
b10100 #
b0100 $
b0101 '
b10100 (
b0100 )
b1100110 *
#2460000000
b0110 "
b10101 #
b0101 $
b0110 '
b10101 (
b0101 )
b1101101 *
#2470000000
b0111 "
b10110 #
b0110 $
b0111 '
b10110 (
b0110 )
b1111101 *
#2480000000
b1000 "
b10111 #
b0111 $
b1000 '
b10111 (
b0111 )
b0000111 *
#2490000000
b1001 "
b11000 #
b1000 $
b1001 '
b11000 (
b1000 )
b1111111 *
#2500000000
b1010 "
b11001 #
b1001 $
b1010 '
b11001 (
b1001 )
b1101111 *
#2510000000
b1011 "
b11010 #
b1010 $
b1011 '
b11010 (
b1010 )
b1110111 *
#2520000000
b1100 "
b11011 #
b1011 $
b1100 '
b11011 (
b1011 )
b1111100 *
#2530000000
b1101 "
b11100 #
b1100 $
b1101 '
b11100 (
b1100 )
b0111001 *
